flazsurvey/__init__.py
flazsurvey/lib.py
flazsurvey-0.0.8.dist-info/LICENSE.txt
flazsurvey-0.0.8.dist-info/METADATA
flazsurvey-0.0.8.dist-info/WHEEL
flazsurvey-0.0.8.dist-info/top_level.txt
flazsurvey-0.0.8.dist-info/RECORD
